term_wrapper/__init__.py
term_wrapper/api.py
term_wrapper/cli.py
term_wrapper/screen_buffer.py
term_wrapper/server.py
term_wrapper/server_manager.py
term_wrapper/session_manager.py
term_wrapper/terminal.py
term_wrapper/utils.py
term_wrapper/frontend/app.js
term_wrapper/frontend/index.html
term_wrapper/frontend/scrolling.js
term_wrapper/frontend/style.css
term_wrapper-0.7.5.dist-info/METADATA
term_wrapper-0.7.5.dist-info/WHEEL
term_wrapper-0.7.5.dist-info/entry_points.txt
term_wrapper-0.7.5.dist-info/licenses/LICENSE
term_wrapper-0.7.5.dist-info/RECORD
