Metadata-Version: 2.4
Name: term-wrapper
Version: 0.7.5
Summary: PTY-based terminal emulator with web backend for running TUI applications via HTTP/WebSocket APIs
Project-URL: Homepage, https://github.com/rom1504/term-wrapper
Project-URL: Repository, https://github.com/rom1504/term-wrapper
Project-URL: Issues, https://github.com/rom1504/term-wrapper/issues
Author-email: Romain Beaumont <romain.rom1@gmail.com>
License: MIT
License-File: LICENSE
Keywords: fastapi,pty,terminal,terminal-emulator,tui,vim,webserver,websocket
Classifier: Development Status :: 4 - Beta
Classifier: Intended Audience :: Developers
Classifier: License :: OSI Approved :: MIT License
Classifier: Programming Language :: Python :: 3
Classifier: Programming Language :: Python :: 3.12
Classifier: Topic :: Software Development :: Libraries :: Python Modules
Classifier: Topic :: System :: Shells
Classifier: Topic :: Terminals
Requires-Python: >=3.12
Requires-Dist: fastapi>=0.128.0
Requires-Dist: httpx>=0.28.1
Requires-Dist: uvicorn>=0.40.0
Requires-Dist: websockets>=16.0
Provides-Extra: dev
Requires-Dist: pytest-asyncio>=1.3.0; extra == 'dev'
Requires-Dist: pytest>=9.0.2; extra == 'dev'
